pin_payments/__init__.py
pin_payments/apple_pay.py
pin_payments/authorisations.py
pin_payments/balance.py
pin_payments/bank_accounts.py
pin_payments/base.py
pin_payments/cards.py
pin_payments/charge_service.py
pin_payments/charges.py
pin_payments/currencies.py
pin_payments/customers.py
pin_payments/deposits.py
pin_payments/disputes.py
pin_payments/events.py
pin_payments/files.py
pin_payments/merchants.py
pin_payments/payment_sources.py
pin_payments/plans.py
pin_payments/recipients.py
pin_payments/refunds.py
pin_payments/subscriptions.py
pin_payments/transfers.py
pin_payments/webhooks.py
pin_payments/webhooks_endpoints.py
python_pin_payments-0.1.1.dist-info/LICENSE.md
python_pin_payments-0.1.1.dist-info/METADATA
python_pin_payments-0.1.1.dist-info/WHEEL
python_pin_payments-0.1.1.dist-info/RECORD
