Metadata-Version: 2.1
Name: python-pin-payments
Version: 0.1.1
Summary: Python library for interacting with the Pin Payments API
Home-page: https://github.com/Onix-Systems/python-pin-payments
License: MIT
Author: Viacheslav Lisovoi
Author-email: viacheslav.lisovoi@onix-systems.com
Requires-Python: >=3.10,<4.0
Classifier: License :: OSI Approved :: MIT License
Classifier: Operating System :: OS Independent
Classifier: Programming Language :: Python :: 3
Classifier: Programming Language :: Python :: 3.10
Classifier: Programming Language :: Python :: 3.11
Classifier: Programming Language :: Python :: 3.12
Requires-Dist: python-dotenv (>=0.10.2,<1.0.0)
Requires-Dist: requests (>=2.32.3,<3.0.0)
Requires-Dist: sphinx (>=8.1.3,<9.0.0)
Requires-Dist: sphinx-rtd-theme (>=3.0.2,<4.0.0)
Project-URL: Bug Tracker, https://github.com/Onix-Systems/python-pin-payments/issues
Project-URL: Documentation, https://python-pin-payments.readthedocs.io/en/latest/overview.html
Project-URL: Repository, https://github.com/Onix-Systems/python-pin-payments
